<?xml version='1.0' encoding='UTF-8'?>
<?xml-stylesheet type="text/xsl" href="psplibdocdisplay.xsl" ?>
<PSPLIBDOC>
  <PRXFILES>
    <PRXFILE>
      <PRX>skype_plugin.prx</PRX>
      <PRXNAME>skype_plugin</PRXNAME>
      <LIBRARIES>
        <LIBRARY>
          <NAME>vsh</NAME>
          <FLAGS>0x00010011</FLAGS>
          <FUNCTIONS>
            <FUNCTION>
              <NID>0xB6992B49</NID>
              <NAME>vsh_B6992B49</NAME>
            </FUNCTION>
            <FUNCTION>
              <NID>0xCE60FF36</NID>
              <NAME>vsh_CE60FF36</NAME>
            </FUNCTION>
            <FUNCTION>
              <NID>0xEF042F9F</NID>
              <NAME>vsh_EF042F9F</NAME>
            </FUNCTION>
            <FUNCTION>
              <NID>0xFB7463D4</NID>
              <NAME>vsh_FB7463D4</NAME>
            </FUNCTION>
          </FUNCTIONS>
        </LIBRARY>
        <LIBRARY>
          <NAME>sceVshCommonGui</NAME>
          <FLAGS>0x00010011</FLAGS>
          <FUNCTIONS>
            <FUNCTION>
              <NID>0x5425000B</NID>
              <NAME>sceVshCommonGui_5425000B</NAME>
            </FUNCTION>
            <FUNCTION>
              <NID>0x9A883487</NID>
              <NAME>sceVshCommonGui_9A883487</NAME>
            </FUNCTION>
          </FUNCTIONS>
        </LIBRARY>
        <LIBRARY>
          <NAME>sceVshCommonUtil</NAME>
          <FLAGS>0x00010011</FLAGS>
          <FUNCTIONS>
            <FUNCTION>
              <NID>0x33C33450</NID>
              <NAME>sceVshCommonUtil_33C33450</NAME>
            </FUNCTION>
            <FUNCTION>
              <NID>0x36F77DAA</NID>
              <NAME>sceVshCommonUtil_36F77DAA</NAME>
            </FUNCTION>
            <FUNCTION>
              <NID>0x46A851A2</NID>
              <NAME>sceVshCommonUtil_46A851A2</NAME>
            </FUNCTION>
            <FUNCTION>
              <NID>0x62826787</NID>
              <NAME>sceVshCommonUtil_62826787</NAME>
            </FUNCTION>
            <FUNCTION>
              <NID>0xB58FDC0E</NID>
              <NAME>sceVshCommonUtil_B58FDC0E</NAME>
            </FUNCTION>
            <FUNCTION>
              <NID>0xBCA9CB1C</NID>
              <NAME>sceVshCommonUtil_BCA9CB1C</NAME>
            </FUNCTION>
          </FUNCTIONS>
        </LIBRARY>
        <LIBRARY>
          <NAME>scePaf</NAME>
          <FLAGS>0x00010011</FLAGS>
          <FUNCTIONS>
            <FUNCTION>
              <NID>0x05A03664</NID>
              <NAME>scePaf_05A03664</NAME>
            </FUNCTION>
            <FUNCTION>
              <NID>0x11A22A1E</NID>
              <NAME>scePaf_11A22A1E</NAME>
            </FUNCTION>
            <FUNCTION>
              <NID>0x15415986</NID>
              <NAME>scePaf_15415986</NAME>
            </FUNCTION>
            <FUNCTION>
              <NID>0x1916386E</NID>
              <NAME>scePaf_1916386E</NAME>
            </FUNCTION>
            <FUNCTION>
              <NID>0x21994500</NID>
              <NAME>scePaf_21994500</NAME>
            </FUNCTION>
            <FUNCTION>
              <NID>0x2ACFF23C</NID>
              <NAME>scePaf_2ACFF23C</NAME>
            </FUNCTION>
            <FUNCTION>
              <NID>0x30B6CF2D</NID>
              <NAME>scePaf_30B6CF2D</NAME>
            </FUNCTION>
            <FUNCTION>
              <NID>0x439B12B5</NID>
              <NAME>scePaf_439B12B5</NAME>
            </FUNCTION>
            <FUNCTION>
              <NID>0x454E65B1</NID>
              <NAME>scePaf_454E65B1</NAME>
            </FUNCTION>
            <FUNCTION>
              <NID>0x5CF3208B</NID>
              <NAME>scePaf_5CF3208B</NAME>
            </FUNCTION>
            <FUNCTION>
              <NID>0x5F6E1736</NID>
              <NAME>scePaf_5F6E1736</NAME>
            </FUNCTION>
            <FUNCTION>
              <NID>0x60E5625F</NID>
              <NAME>scePaf_60E5625F</NAME>
            </FUNCTION>
            <FUNCTION>
              <NID>0x690D7FCD</NID>
              <NAME>scePaf_690D7FCD</NAME>
            </FUNCTION>
            <FUNCTION>
              <NID>0x76599DD5</NID>
              <NAME>scePaf_76599DD5</NAME>
            </FUNCTION>
            <FUNCTION>
              <NID>0x7D0AB7A5</NID>
              <NAME>scePaf_7D0AB7A5</NAME>
            </FUNCTION>
            <FUNCTION>
              <NID>0x80157C18</NID>
              <NAME>scePaf_80157C18</NAME>
            </FUNCTION>
            <FUNCTION>
              <NID>0x9165DA3D</NID>
              <NAME>scePaf_9165DA3D</NAME>
            </FUNCTION>
            <FUNCTION>
              <NID>0x9409A30A</NID>
              <NAME>scePaf_9409A30A</NAME>
            </FUNCTION>
            <FUNCTION>
              <NID>0xBA091744</NID>
              <NAME>scePaf_BA091744</NAME>
            </FUNCTION>
            <FUNCTION>
              <NID>0xBAB92246</NID>
              <NAME>scePaf_BAB92246</NAME>
            </FUNCTION>
            <FUNCTION>
              <NID>0xBAFBE2FE</NID>
              <NAME>scePaf_BAFBE2FE</NAME>
            </FUNCTION>
            <FUNCTION>
              <NID>0xC81EA5CB</NID>
              <NAME>scePaf_C81EA5CB</NAME>
            </FUNCTION>
            <FUNCTION>
              <NID>0xCA3515A2</NID>
              <NAME>scePaf_CA3515A2</NAME>
            </FUNCTION>
            <FUNCTION>
              <NID>0xDFA189A2</NID>
              <NAME>scePaf_DFA189A2</NAME>
            </FUNCTION>
            <FUNCTION>
              <NID>0xE02EAF2E</NID>
              <NAME>scePaf_E02EAF2E</NAME>
            </FUNCTION>
            <FUNCTION>
              <NID>0xE2934239</NID>
              <NAME>scePaf_E2934239</NAME>
            </FUNCTION>
            <FUNCTION>
              <NID>0xE61235DB</NID>
              <NAME>scePaf_E61235DB</NAME>
            </FUNCTION>
            <FUNCTION>
              <NID>0xE7A2A7BF</NID>
              <NAME>scePaf_E7A2A7BF</NAME>
            </FUNCTION>
            <FUNCTION>
              <NID>0xF97E8F8A</NID>
              <NAME>scePaf_F97E8F8A</NAME>
            </FUNCTION>
            <FUNCTION>
              <NID>0xFD46CF9D</NID>
              <NAME>scePaf_FD46CF9D</NAME>
            </FUNCTION>
            <FUNCTION>
              <NID>0xFD9C8660</NID>
              <NAME>scePaf_FD9C8660</NAME>
            </FUNCTION>
          </FUNCTIONS>
          <VARIABLES>
            <VARIABLE>
              <NID>0xBAC57301</NID>
              <NAME>scePaf_BAC57301</NAME>
            </VARIABLE>
          </VARIABLES>
        </LIBRARY>
        <LIBRARY>
          <NAME>sceNetApctl</NAME>
          <FLAGS>0x00090011</FLAGS>
          <FUNCTIONS>
            <FUNCTION>
              <NID>0x5DEAC81B</NID>
              <NAME>sceNetApctlGetState</NAME>
            </FUNCTION>
            <FUNCTION>
              <NID>0x6F5D2981</NID>
              <NAME>sceNetApctl_6F5D2981</NAME>
            </FUNCTION>
            <FUNCTION>
              <NID>0xA7BB73DF</NID>
              <NAME>sceNetApctl_A7BB73DF</NAME>
            </FUNCTION>
          </FUNCTIONS>
        </LIBRARY>
        <LIBRARY>
          <NAME>sceVshBridge</NAME>
          <FLAGS>0x40010011</FLAGS>
          <FUNCTIONS>
            <FUNCTION>
              <NID>0x049773F6</NID>
              <NAME>sceVshBridge_049773F6</NAME>
            </FUNCTION>
            <FUNCTION>
              <NID>0x33827469</NID>
              <NAME>sceVshBridge_33827469</NAME>
            </FUNCTION>
            <FUNCTION>
              <NID>0x6BEBCAF4</NID>
              <NAME>sceVshBridge_6BEBCAF4</NAME>
            </FUNCTION>
          </FUNCTIONS>
        </LIBRARY>
        <LIBRARY>
          <NAME>Kernel_Library</NAME>
          <FLAGS>0x00010011</FLAGS>
          <FUNCTIONS>
            <FUNCTION>
              <NID>0x15B6446B</NID>
              <NAME>sceKernelUnlockLwMutex</NAME>
            </FUNCTION>
            <FUNCTION>
              <NID>0xBEA46419</NID>
              <NAME>sceKernelLockLwMutex</NAME>
            </FUNCTION>
          </FUNCTIONS>
        </LIBRARY>
        <LIBRARY>
          <NAME>ThreadManForUser</NAME>
          <FLAGS>0x40010011</FLAGS>
          <FUNCTIONS>
            <FUNCTION>
              <NID>0xC07BB470</NID>
              <NAME>sceKernelCreateFpl</NAME>
            </FUNCTION>
            <FUNCTION>
              <NID>0xE81CAF8F</NID>
              <NAME>sceKernelCreateCallback</NAME>
            </FUNCTION>
            <FUNCTION>
              <NID>0xED1410E0</NID>
              <NAME>sceKernelDeleteFpl</NAME>
            </FUNCTION>
            <FUNCTION>
              <NID>0xEDBA5844</NID>
              <NAME>sceKernelDeleteCallback</NAME>
            </FUNCTION>
            <FUNCTION>
              <NID>0xF6414A71</NID>
              <NAME>sceKernelFreeFpl</NAME>
            </FUNCTION>
            <FUNCTION>
              <NID>0x349D6D6C</NID>
              <NAME>sceKernelCheckCallback</NAME>
            </FUNCTION>
            <FUNCTION>
              <NID>0x60107536</NID>
              <NAME>sceKernelDeleteLwMutex</NAME>
            </FUNCTION>
            <FUNCTION>
              <NID>0x623AE665</NID>
              <NAME>sceKernelTryAllocateFpl</NAME>
            </FUNCTION>
            <FUNCTION>
              <NID>0x19CFF145</NID>
              <NAME>sceKernelCreateLwMutex</NAME>
            </FUNCTION>
          </FUNCTIONS>
        </LIBRARY>
        <LIBRARY>
          <NAME>sceUsb</NAME>
          <FLAGS>0x40010011</FLAGS>
          <FUNCTIONS>
            <FUNCTION>
              <NID>0x5BE0E002</NID>
              <NAME>sceUsbWaitState</NAME>
            </FUNCTION>
          </FUNCTIONS>
        </LIBRARY>
        <LIBRARY>
          <NAME>sceUsbAcc</NAME>
          <FLAGS>0x40090011</FLAGS>
          <FUNCTIONS>
            <FUNCTION>
              <NID>0x79A1C743</NID>
              <NAME>sceUsbAccGetAuthStat</NAME>
            </FUNCTION>
          </FUNCTIONS>
        </LIBRARY>
      </LIBRARIES>
    </PRXFILE>
  </PRXFILES>
</PSPLIBDOC>
