<?xml version='1.0' encoding='UTF-8'?>
<?xml-stylesheet type="text/xsl" href="psplibdocdisplay.xsl" ?>
<PSPLIBDOC>
  <PRXFILES>
    <PRXFILE>
      <PRX>opening_plugin.prx</PRX>
      <PRXNAME>opening_plugin_module</PRXNAME>
      <LIBRARIES>
        <LIBRARY>
          <NAME>sceVshCommonUtil</NAME>
          <FLAGS>0x00010011</FLAGS>
          <FUNCTIONS>
            <FUNCTION>
              <NID>0x1D7E0B27</NID>
              <NAME>sceVshCommonUtil_1D7E0B27</NAME>
            </FUNCTION>
            <FUNCTION>
              <NID>0x2058CEAA</NID>
              <NAME>sceVshCommonUtil_2058CEAA</NAME>
            </FUNCTION>
            <FUNCTION>
              <NID>0x34826464</NID>
              <NAME>sceVshCommonUtil_34826464</NAME>
            </FUNCTION>
          </FUNCTIONS>
        </LIBRARY>
        <LIBRARY>
          <NAME>vsh</NAME>
          <FLAGS>0x00010011</FLAGS>
          <FUNCTIONS>
            <FUNCTION>
              <NID>0xB8365DF7</NID>
              <NAME>vsh_B8365DF7</NAME>
            </FUNCTION>
          </FUNCTIONS>
        </LIBRARY>
        <LIBRARY>
          <NAME>scePaf</NAME>
          <FLAGS>0x00010011</FLAGS>
          <FUNCTIONS>
            <FUNCTION>
              <NID>0x0B95292E</NID>
              <NAME>scePaf_0B95292E</NAME>
            </FUNCTION>
            <FUNCTION>
              <NID>0x0C2CD696</NID>
              <NAME>scePaf_0C2CD696</NAME>
            </FUNCTION>
            <FUNCTION>
              <NID>0x0EE8FFFF</NID>
              <NAME>scePaf_0EE8FFFF</NAME>
            </FUNCTION>
            <FUNCTION>
              <NID>0x279F57C3</NID>
              <NAME>scePaf_279F57C3</NAME>
            </FUNCTION>
            <FUNCTION>
              <NID>0x2C0F0975</NID>
              <NAME>scePaf_2C0F0975</NAME>
            </FUNCTION>
            <FUNCTION>
              <NID>0x2D92A298</NID>
              <NAME>scePaf_2D92A298</NAME>
            </FUNCTION>
            <FUNCTION>
              <NID>0x379A3D64</NID>
              <NAME>scePaf_379A3D64</NAME>
            </FUNCTION>
            <FUNCTION>
              <NID>0x3876721B</NID>
              <NAME>scePaf_3876721B</NAME>
            </FUNCTION>
            <FUNCTION>
              <NID>0x3A4504D5</NID>
              <NAME>scePaf_3A4504D5</NAME>
            </FUNCTION>
            <FUNCTION>
              <NID>0x412B2F09</NID>
              <NAME>scePaf_412B2F09</NAME>
            </FUNCTION>
            <FUNCTION>
              <NID>0x430D11DC</NID>
              <NAME>scePaf_430D11DC</NAME>
            </FUNCTION>
            <FUNCTION>
              <NID>0x440665DB</NID>
              <NAME>scePaf_440665DB</NAME>
            </FUNCTION>
            <FUNCTION>
              <NID>0x4AF28AF7</NID>
              <NAME>scePaf_4AF28AF7</NAME>
            </FUNCTION>
            <FUNCTION>
              <NID>0x4CF09BA2</NID>
              <NAME>scePaf_4CF09BA2</NAME>
            </FUNCTION>
            <FUNCTION>
              <NID>0x4F4F4838</NID>
              <NAME>scePaf_4F4F4838</NAME>
            </FUNCTION>
            <FUNCTION>
              <NID>0x53B0C35F</NID>
              <NAME>scePaf_53B0C35F</NAME>
            </FUNCTION>
            <FUNCTION>
              <NID>0x5A6CAFE2</NID>
              <NAME>scePaf_5A6CAFE2</NAME>
            </FUNCTION>
            <FUNCTION>
              <NID>0x5E909060</NID>
              <NAME>scePaf_5E909060</NAME>
            </FUNCTION>
            <FUNCTION>
              <NID>0x675047B1</NID>
              <NAME>scePaf_675047B1</NAME>
            </FUNCTION>
            <FUNCTION>
              <NID>0x698098B9</NID>
              <NAME>scePaf_698098B9</NAME>
            </FUNCTION>
            <FUNCTION>
              <NID>0x73DA59C1</NID>
              <NAME>scePaf_73DA59C1</NAME>
            </FUNCTION>
            <FUNCTION>
              <NID>0x77ADEAEB</NID>
              <NAME>scePaf_77ADEAEB</NAME>
            </FUNCTION>
            <FUNCTION>
              <NID>0x7B7133D5</NID>
              <NAME>scePaf_7B7133D5</NAME>
            </FUNCTION>
            <FUNCTION>
              <NID>0x7B77B7E7</NID>
              <NAME>scePaf_7B77B7E7</NAME>
            </FUNCTION>
            <FUNCTION>
              <NID>0x7D7DEB7E</NID>
              <NAME>scePaf_7D7DEB7E</NAME>
            </FUNCTION>
            <FUNCTION>
              <NID>0x7E0A6B25</NID>
              <NAME>scePaf_7E0A6B25</NAME>
            </FUNCTION>
            <FUNCTION>
              <NID>0x8BC9927A</NID>
              <NAME>scePaf_8BC9927A</NAME>
            </FUNCTION>
            <FUNCTION>
              <NID>0x94B00628</NID>
              <NAME>scePaf_94B00628</NAME>
            </FUNCTION>
            <FUNCTION>
              <NID>0x995294D1</NID>
              <NAME>scePaf_995294D1</NAME>
            </FUNCTION>
            <FUNCTION>
              <NID>0x9AF12ADC</NID>
              <NAME>scePaf_9AF12ADC</NAME>
            </FUNCTION>
            <FUNCTION>
              <NID>0x9EEFEF9D</NID>
              <NAME>scePaf_9EEFEF9D</NAME>
            </FUNCTION>
            <FUNCTION>
              <NID>0x9F12D4D1</NID>
              <NAME>scePaf_9F12D4D1</NAME>
            </FUNCTION>
            <FUNCTION>
              <NID>0x9F3E4ED9</NID>
              <NAME>scePaf_9F3E4ED9</NAME>
            </FUNCTION>
            <FUNCTION>
              <NID>0xA4EAD0A0</NID>
              <NAME>scePaf_A4EAD0A0</NAME>
            </FUNCTION>
            <FUNCTION>
              <NID>0xB6D58D98</NID>
              <NAME>scePaf_B6D58D98</NAME>
            </FUNCTION>
            <FUNCTION>
              <NID>0xB94AD2A4</NID>
              <NAME>scePaf_B94AD2A4</NAME>
            </FUNCTION>
            <FUNCTION>
              <NID>0xD1B09FDC</NID>
              <NAME>scePaf_D1B09FDC</NAME>
            </FUNCTION>
            <FUNCTION>
              <NID>0xD5F2C162</NID>
              <NAME>scePaf_D5F2C162</NAME>
            </FUNCTION>
            <FUNCTION>
              <NID>0xD7DCB972</NID>
              <NAME>scePaf_D7DCB972</NAME>
            </FUNCTION>
            <FUNCTION>
              <NID>0xD82DE86E</NID>
              <NAME>scePaf_D82DE86E</NAME>
            </FUNCTION>
            <FUNCTION>
              <NID>0xE6D56019</NID>
              <NAME>scePaf_E6D56019</NAME>
            </FUNCTION>
            <FUNCTION>
              <NID>0xF4C130B8</NID>
              <NAME>scePaf_F4C130B8</NAME>
            </FUNCTION>
          </FUNCTIONS>
          <VARIABLES>
            <VARIABLE>
              <NID>0x421A7BDD</NID>
              <NAME>scePaf_421A7BDD</NAME>
            </VARIABLE>
            <VARIABLE>
              <NID>0xB52933D3</NID>
              <NAME>scePaf_B52933D3</NAME>
            </VARIABLE>
          </VARIABLES>
        </LIBRARY>
        <LIBRARY>
          <NAME>scePower</NAME>
          <FLAGS>0x40010011</FLAGS>
          <FUNCTIONS>
            <FUNCTION>
              <NID>0x469989AD</NID>
              <NAME>scePower_469989AD</NAME>
            </FUNCTION>
            <FUNCTION>
              <NID>0xDB62C9CF</NID>
              <NAME>scePowerCancelRequest</NAME>
            </FUNCTION>
          </FUNCTIONS>
        </LIBRARY>
        <LIBRARY>
          <NAME>sceAtrac3plus</NAME>
          <FLAGS>0x00090011</FLAGS>
          <FUNCTIONS>
            <FUNCTION>
              <NID>0x5D268707</NID>
              <NAME>sceAtracGetStreamDataInfo</NAME>
            </FUNCTION>
            <FUNCTION>
              <NID>0x61EB33F5</NID>
              <NAME>sceAtracReleaseAtracID</NAME>
            </FUNCTION>
            <FUNCTION>
              <NID>0x6A8C3CD5</NID>
              <NAME>sceAtracDecodeData</NAME>
            </FUNCTION>
            <FUNCTION>
              <NID>0x7A20E7AF</NID>
              <NAME>sceAtracSetDataAndGetID</NAME>
            </FUNCTION>
            <FUNCTION>
              <NID>0x7DB31251</NID>
              <NAME>sceAtracAddStreamData</NAME>
            </FUNCTION>
            <FUNCTION>
              <NID>0x83BF7AFD</NID>
              <NAME>sceAtracSetSecondBuffer</NAME>
            </FUNCTION>
            <FUNCTION>
              <NID>0x83E85EA0</NID>
              <NAME>sceAtracGetSecondBufferInfo</NAME>
            </FUNCTION>
            <FUNCTION>
              <NID>0x868120B5</NID>
              <NAME>sceAtracSetLoopNum</NAME>
            </FUNCTION>
            <FUNCTION>
              <NID>0x9AE849A7</NID>
              <NAME>sceAtracGetRemainFrame</NAME>
            </FUNCTION>
            <FUNCTION>
              <NID>0xA2BBA8BE</NID>
              <NAME>sceAtracGetSoundSample</NAME>
            </FUNCTION>
            <FUNCTION>
              <NID>0xE23E3A35</NID>
              <NAME>sceAtracGetNextDecodePosition</NAME>
            </FUNCTION>
            <FUNCTION>
              <NID>0xE88F759B</NID>
              <NAME>sceAtracGetInternalErrorInfo</NAME>
            </FUNCTION>
          </FUNCTIONS>
        </LIBRARY>
        <LIBRARY>
          <NAME>sceAudio</NAME>
          <FLAGS>0x40010011</FLAGS>
          <FUNCTIONS>
            <FUNCTION>
              <NID>0x136CAF51</NID>
              <NAME>sceAudioOutputBlocking</NAME>
            </FUNCTION>
            <FUNCTION>
              <NID>0x13F592BC</NID>
              <NAME>sceAudioOutputPannedBlocking</NAME>
            </FUNCTION>
            <FUNCTION>
              <NID>0x5EC81C55</NID>
              <NAME>sceAudioChReserve</NAME>
            </FUNCTION>
            <FUNCTION>
              <NID>0x6FC46853</NID>
              <NAME>sceAudioChRelease</NAME>
            </FUNCTION>
            <FUNCTION>
              <NID>0x95FD0C2D</NID>
              <NAME>sceAudioChangeChannelConfig</NAME>
            </FUNCTION>
            <FUNCTION>
              <NID>0xB011922F</NID>
              <NAME>sceAudioGetChannelRestLength</NAME>
            </FUNCTION>
            <FUNCTION>
              <NID>0xB7E1D8E7</NID>
              <NAME>sceAudioChangeChannelVolume</NAME>
            </FUNCTION>
            <FUNCTION>
              <NID>0xCB2E439E</NID>
              <NAME>sceAudioSetChannelDataLen</NAME>
            </FUNCTION>
            <FUNCTION>
              <NID>0xE2D56B2D</NID>
              <NAME>sceAudioOutputPanned</NAME>
            </FUNCTION>
          </FUNCTIONS>
        </LIBRARY>
        <LIBRARY>
          <NAME>Kernel_Library</NAME>
          <FLAGS>0x00010011</FLAGS>
          <FUNCTIONS>
            <FUNCTION>
              <NID>0xA089ECA4</NID>
              <NAME>sceKernelMemset</NAME>
            </FUNCTION>
            <FUNCTION>
              <NID>0x1839852A</NID>
              <NAME>sceKernelMemcpy</NAME>
            </FUNCTION>
          </FUNCTIONS>
        </LIBRARY>
        <LIBRARY>
          <NAME>sceSuspendForUser</NAME>
          <FLAGS>0x40000011</FLAGS>
          <FUNCTIONS>
            <FUNCTION>
              <NID>0x3AEE7261</NID>
              <NAME>sceKernelPowerUnlock</NAME>
            </FUNCTION>
            <FUNCTION>
              <NID>0xEADB1BD7</NID>
              <NAME>sceKernelPowerLock</NAME>
            </FUNCTION>
          </FUNCTIONS>
        </LIBRARY>
        <LIBRARY>
          <NAME>ThreadManForUser</NAME>
          <FLAGS>0x40010011</FLAGS>
          <FUNCTIONS>
            <FUNCTION>
              <NID>0xCEADEB47</NID>
              <NAME>sceKernelDelayThread</NAME>
            </FUNCTION>
            <FUNCTION>
              <NID>0xEF9E4C70</NID>
              <NAME>sceKernelDeleteEventFlag</NAME>
            </FUNCTION>
            <FUNCTION>
              <NID>0x1FB15A32</NID>
              <NAME>sceKernelSetEventFlag</NAME>
            </FUNCTION>
            <FUNCTION>
              <NID>0xF475845D</NID>
              <NAME>sceKernelStartThread</NAME>
            </FUNCTION>
            <FUNCTION>
              <NID>0x278C0DF5</NID>
              <NAME>sceKernelWaitThreadEnd</NAME>
            </FUNCTION>
            <FUNCTION>
              <NID>0x402FCF22</NID>
              <NAME>sceKernelWaitEventFlag</NAME>
            </FUNCTION>
            <FUNCTION>
              <NID>0x446D8DE6</NID>
              <NAME>sceKernelCreateThread</NAME>
            </FUNCTION>
            <FUNCTION>
              <NID>0x55C20A00</NID>
              <NAME>sceKernelCreateEventFlag</NAME>
            </FUNCTION>
            <FUNCTION>
              <NID>0x809CE29B</NID>
              <NAME>sceKernelExitDeleteThread</NAME>
            </FUNCTION>
            <FUNCTION>
              <NID>0x9FA03CD3</NID>
              <NAME>sceKernelDeleteThread</NAME>
            </FUNCTION>
            <FUNCTION>
              <NID>0xAA73C935</NID>
              <NAME>sceKernelExitThread</NAME>
            </FUNCTION>
          </FUNCTIONS>
        </LIBRARY>
      </LIBRARIES>
    </PRXFILE>
  </PRXFILES>
</PSPLIBDOC>
