<?xml version='1.0' encoding='UTF-8'?>
<?xml-stylesheet type="text/xsl" href="psplibdocdisplay.xsl" ?>
<PSPLIBDOC>
  <PRXFILES>
    <PRXFILE>
      <PRX>subs_plugin.prx</PRX>
      <PRXNAME>sceVshSubsPlugin_Module</PRXNAME>
      <LIBRARIES>
        <LIBRARY>
          <NAME>sceVshCommonGui</NAME>
          <FLAGS>0x00010011</FLAGS>
          <FUNCTIONS>
            <FUNCTION>
              <NID>0x09E310BB</NID>
              <NAME>sceVshCommonGui_09E310BB</NAME>
            </FUNCTION>
            <FUNCTION>
              <NID>0x1057556E</NID>
              <NAME>sceVshCommonGui_1057556E</NAME>
            </FUNCTION>
            <FUNCTION>
              <NID>0x20C594B7</NID>
              <NAME>sceVshCommonGui_20C594B7</NAME>
            </FUNCTION>
            <FUNCTION>
              <NID>0x460C32EF</NID>
              <NAME>sceVshCommonGui_460C32EF</NAME>
            </FUNCTION>
            <FUNCTION>
              <NID>0x48D6E2B0</NID>
              <NAME>sceVshCommonGui_48D6E2B0</NAME>
            </FUNCTION>
            <FUNCTION>
              <NID>0x51FC9D2D</NID>
              <NAME>sceVshCommonGui_51FC9D2D</NAME>
            </FUNCTION>
            <FUNCTION>
              <NID>0x53EE2FDB</NID>
              <NAME>sceVshCommonGui_53EE2FDB</NAME>
            </FUNCTION>
            <FUNCTION>
              <NID>0x5A66D859</NID>
              <NAME>sceVshCommonGui_5A66D859</NAME>
            </FUNCTION>
            <FUNCTION>
              <NID>0x6487FB2D</NID>
              <NAME>sceVshCommonGui_6487FB2D</NAME>
            </FUNCTION>
            <FUNCTION>
              <NID>0x7ABC27D3</NID>
              <NAME>sceVshCommonGui_7ABC27D3</NAME>
            </FUNCTION>
            <FUNCTION>
              <NID>0xA80AB1AC</NID>
              <NAME>sceVshCommonGui_A80AB1AC</NAME>
            </FUNCTION>
            <FUNCTION>
              <NID>0xBFD877D3</NID>
              <NAME>sceVshCommonGui_BFD877D3</NAME>
            </FUNCTION>
            <FUNCTION>
              <NID>0xC49F3B83</NID>
              <NAME>sceVshCommonGui_C49F3B83</NAME>
            </FUNCTION>
            <FUNCTION>
              <NID>0xF72D6FEF</NID>
              <NAME>sceVshCommonGui_F72D6FEF</NAME>
            </FUNCTION>
          </FUNCTIONS>
        </LIBRARY>
        <LIBRARY>
          <NAME>sceVshCommonUtil</NAME>
          <FLAGS>0x00010011</FLAGS>
          <FUNCTIONS>
            <FUNCTION>
              <NID>0x2EC30FC1</NID>
              <NAME>sceVshCommonUtil_2EC30FC1</NAME>
            </FUNCTION>
            <FUNCTION>
              <NID>0x87D6D82A</NID>
              <NAME>sceVshCommonUtil_87D6D82A</NAME>
            </FUNCTION>
            <FUNCTION>
              <NID>0xE8A03BAF</NID>
              <NAME>sceVshCommonUtil_E8A03BAF</NAME>
            </FUNCTION>
          </FUNCTIONS>
        </LIBRARY>
        <LIBRARY>
          <NAME>scePaf</NAME>
          <FLAGS>0x00010011</FLAGS>
          <FUNCTIONS>
            <FUNCTION>
              <NID>0x02257928</NID>
              <NAME>scePaf_02257928</NAME>
            </FUNCTION>
            <FUNCTION>
              <NID>0x03C8C2CB</NID>
              <NAME>scePaf_03C8C2CB</NAME>
            </FUNCTION>
            <FUNCTION>
              <NID>0x0D22E146</NID>
              <NAME>scePaf_0D22E146</NAME>
            </FUNCTION>
            <FUNCTION>
              <NID>0x1AD7BA6C</NID>
              <NAME>scePaf_1AD7BA6C</NAME>
            </FUNCTION>
            <FUNCTION>
              <NID>0x1B952318</NID>
              <NAME>scePaf_1B952318</NAME>
            </FUNCTION>
            <FUNCTION>
              <NID>0x1E7DAB2C</NID>
              <NAME>scePaf_1E7DAB2C</NAME>
            </FUNCTION>
            <FUNCTION>
              <NID>0x1F538758</NID>
              <NAME>scePaf_1F538758</NAME>
            </FUNCTION>
            <FUNCTION>
              <NID>0x296C75A5</NID>
              <NAME>scePaf_296C75A5</NAME>
            </FUNCTION>
            <FUNCTION>
              <NID>0x37CBE39F</NID>
              <NAME>scePaf_37CBE39F</NAME>
            </FUNCTION>
            <FUNCTION>
              <NID>0x3C6D0742</NID>
              <NAME>scePaf_3C6D0742</NAME>
            </FUNCTION>
            <FUNCTION>
              <NID>0x3DC4FCD9</NID>
              <NAME>scePaf_3DC4FCD9</NAME>
            </FUNCTION>
            <FUNCTION>
              <NID>0x46C958E5</NID>
              <NAME>scePaf_46C958E5</NAME>
            </FUNCTION>
            <FUNCTION>
              <NID>0x49A72E5D</NID>
              <NAME>scePaf_49A72E5D</NAME>
            </FUNCTION>
            <FUNCTION>
              <NID>0x4E961D50</NID>
              <NAME>scePaf_4E961D50</NAME>
            </FUNCTION>
            <FUNCTION>
              <NID>0x51701C97</NID>
              <NAME>scePaf_51701C97</NAME>
            </FUNCTION>
            <FUNCTION>
              <NID>0x5377902C</NID>
              <NAME>scePaf_5377902C</NAME>
            </FUNCTION>
            <FUNCTION>
              <NID>0x596B9BB2</NID>
              <NAME>scePaf_596B9BB2</NAME>
            </FUNCTION>
            <FUNCTION>
              <NID>0x5C4F3DE5</NID>
              <NAME>scePaf_5C4F3DE5</NAME>
            </FUNCTION>
            <FUNCTION>
              <NID>0x65664A77</NID>
              <NAME>scePaf_65664A77</NAME>
            </FUNCTION>
            <FUNCTION>
              <NID>0x696021C7</NID>
              <NAME>scePaf_696021C7</NAME>
            </FUNCTION>
            <FUNCTION>
              <NID>0x70082F6F</NID>
              <NAME>scePaf_70082F6F</NAME>
            </FUNCTION>
            <FUNCTION>
              <NID>0x70835917</NID>
              <NAME>scePaf_70835917</NAME>
            </FUNCTION>
            <FUNCTION>
              <NID>0x7B79AF8B</NID>
              <NAME>scePaf_7B79AF8B</NAME>
            </FUNCTION>
            <FUNCTION>
              <NID>0x87245AFE</NID>
              <NAME>scePaf_87245AFE</NAME>
            </FUNCTION>
            <FUNCTION>
              <NID>0x8894D2E6</NID>
              <NAME>scePaf_8894D2E6</NAME>
            </FUNCTION>
            <FUNCTION>
              <NID>0x89E16906</NID>
              <NAME>scePaf_89E16906</NAME>
            </FUNCTION>
            <FUNCTION>
              <NID>0x8F67BFDB</NID>
              <NAME>scePaf_8F67BFDB</NAME>
            </FUNCTION>
            <FUNCTION>
              <NID>0x94A5FCE8</NID>
              <NAME>scePaf_94A5FCE8</NAME>
            </FUNCTION>
            <FUNCTION>
              <NID>0x97D28412</NID>
              <NAME>scePaf_97D28412</NAME>
            </FUNCTION>
            <FUNCTION>
              <NID>0x9892D4F2</NID>
              <NAME>scePaf_9892D4F2</NAME>
            </FUNCTION>
            <FUNCTION>
              <NID>0x9A2A0474</NID>
              <NAME>scePaf_9A2A0474</NAME>
            </FUNCTION>
            <FUNCTION>
              <NID>0x9A7CC83D</NID>
              <NAME>scePaf_9A7CC83D</NAME>
            </FUNCTION>
            <FUNCTION>
              <NID>0x9DE7AD23</NID>
              <NAME>scePaf_9DE7AD23</NAME>
            </FUNCTION>
            <FUNCTION>
              <NID>0x9E9FFBFB</NID>
              <NAME>scePaf_9E9FFBFB</NAME>
            </FUNCTION>
            <FUNCTION>
              <NID>0x9EBFC5A5</NID>
              <NAME>scePaf_9EBFC5A5</NAME>
            </FUNCTION>
            <FUNCTION>
              <NID>0x9FAAC4B8</NID>
              <NAME>scePaf_9FAAC4B8</NAME>
            </FUNCTION>
            <FUNCTION>
              <NID>0xB0363C2E</NID>
              <NAME>scePaf_B0363C2E</NAME>
            </FUNCTION>
            <FUNCTION>
              <NID>0xB1A0654A</NID>
              <NAME>scePaf_B1A0654A</NAME>
            </FUNCTION>
            <FUNCTION>
              <NID>0xB5985FC3</NID>
              <NAME>scePaf_B5985FC3</NAME>
            </FUNCTION>
            <FUNCTION>
              <NID>0xBBA2D269</NID>
              <NAME>scePaf_BBA2D269</NAME>
            </FUNCTION>
            <FUNCTION>
              <NID>0xC2820326</NID>
              <NAME>scePaf_C2820326</NAME>
            </FUNCTION>
            <FUNCTION>
              <NID>0xC2974AF1</NID>
              <NAME>scePaf_C2974AF1</NAME>
            </FUNCTION>
            <FUNCTION>
              <NID>0xCF4241BD</NID>
              <NAME>scePaf_CF4241BD</NAME>
            </FUNCTION>
            <FUNCTION>
              <NID>0xCFF3B854</NID>
              <NAME>scePaf_CFF3B854</NAME>
            </FUNCTION>
            <FUNCTION>
              <NID>0xD38E62C6</NID>
              <NAME>scePaf_D38E62C6</NAME>
            </FUNCTION>
            <FUNCTION>
              <NID>0xD4697673</NID>
              <NAME>scePaf_D4697673</NAME>
            </FUNCTION>
            <FUNCTION>
              <NID>0xDDC7D182</NID>
              <NAME>scePaf_DDC7D182</NAME>
            </FUNCTION>
            <FUNCTION>
              <NID>0xDE69A6CD</NID>
              <NAME>scePaf_DE69A6CD</NAME>
            </FUNCTION>
            <FUNCTION>
              <NID>0xF2B119D3</NID>
              <NAME>scePaf_F2B119D3</NAME>
            </FUNCTION>
            <FUNCTION>
              <NID>0xF4A8DBBF</NID>
              <NAME>scePaf_F4A8DBBF</NAME>
            </FUNCTION>
            <FUNCTION>
              <NID>0xF9C7A22E</NID>
              <NAME>scePaf_F9C7A22E</NAME>
            </FUNCTION>
            <FUNCTION>
              <NID>0xFFC1EE81</NID>
              <NAME>scePaf_FFC1EE81</NAME>
            </FUNCTION>
            <FUNCTION>
              <NID>0xFFEC9718</NID>
              <NAME>scePaf_FFEC9718</NAME>
            </FUNCTION>
          </FUNCTIONS>
          <VARIABLES>
            <VARIABLE>
              <NID>0x7BDDAA08</NID>
              <NAME>scePaf_7BDDAA08</NAME>
            </VARIABLE>
            <VARIABLE>
              <NID>0xED502BA1</NID>
              <NAME>scePaf_ED502BA1</NAME>
            </VARIABLE>
          </VARIABLES>
        </LIBRARY>
        <LIBRARY>
          <NAME>vsh</NAME>
          <FLAGS>0x00090011</FLAGS>
          <FUNCTIONS>
            <FUNCTION>
              <NID>0x20EBE0F1</NID>
              <NAME>vsh_20EBE0F1</NAME>
            </FUNCTION>
            <FUNCTION>
              <NID>0x26253DF4</NID>
              <NAME>vsh_26253DF4</NAME>
            </FUNCTION>
            <FUNCTION>
              <NID>0x42CCB019</NID>
              <NAME>vsh_42CCB019</NAME>
            </FUNCTION>
            <FUNCTION>
              <NID>0x80F139CD</NID>
              <NAME>vsh_80F139CD</NAME>
            </FUNCTION>
          </FUNCTIONS>
        </LIBRARY>
        <LIBRARY>
          <NAME>sceNet</NAME>
          <FLAGS>0x00090011</FLAGS>
          <FUNCTIONS>
            <FUNCTION>
              <NID>0x50647530</NID>
              <NAME>sceNetFreeThreadinfo</NAME>
            </FUNCTION>
          </FUNCTIONS>
        </LIBRARY>
        <LIBRARY>
          <NAME>sceWlanDrv</NAME>
          <FLAGS>0x40010011</FLAGS>
          <FUNCTIONS>
            <FUNCTION>
              <NID>0xD7763699</NID>
              <NAME>sceWlanGetSwitchState</NAME>
            </FUNCTION>
          </FUNCTIONS>
        </LIBRARY>
        <LIBRARY>
          <NAME>Kernel_Library</NAME>
          <FLAGS>0x00010011</FLAGS>
          <FUNCTIONS>
            <FUNCTION>
              <NID>0xA089ECA4</NID>
              <NAME>sceKernelMemset</NAME>
            </FUNCTION>
            <FUNCTION>
              <NID>0x1839852A</NID>
              <NAME>sceKernelMemcpy</NAME>
            </FUNCTION>
            <FUNCTION>
              <NID>0x293B45B8</NID>
              <NAME>sceKernelGetThreadId</NAME>
            </FUNCTION>
          </FUNCTIONS>
        </LIBRARY>
        <LIBRARY>
          <NAME>sceGameUpdate</NAME>
          <FLAGS>0x00090011</FLAGS>
          <FUNCTIONS>
            <FUNCTION>
              <NID>0x381CB9B3</NID>
              <NAME>sceGameUpdate_381CB9B3</NAME>
            </FUNCTION>
            <FUNCTION>
              <NID>0x3EBB6055</NID>
              <NAME>sceGameUpdate_3EBB6055</NAME>
            </FUNCTION>
            <FUNCTION>
              <NID>0x5F5D98A6</NID>
              <NAME>sceGameUpdateAbort</NAME>
            </FUNCTION>
            <FUNCTION>
              <NID>0xBB4B68DE</NID>
              <NAME>sceGameUpdateTerm</NAME>
            </FUNCTION>
            <FUNCTION>
              <NID>0xD92F50CA</NID>
              <NAME>sceGameUpdate_D92F50CA</NAME>
            </FUNCTION>
          </FUNCTIONS>
        </LIBRARY>
        <LIBRARY>
          <NAME>sceNetApctl</NAME>
          <FLAGS>0x00090011</FLAGS>
          <FUNCTIONS>
            <FUNCTION>
              <NID>0x6F5D2981</NID>
              <NAME>sceNetApctl_6F5D2981</NAME>
            </FUNCTION>
            <FUNCTION>
              <NID>0xA7BB73DF</NID>
              <NAME>sceNetApctl_A7BB73DF</NAME>
            </FUNCTION>
          </FUNCTIONS>
        </LIBRARY>
      </LIBRARIES>
    </PRXFILE>
  </PRXFILES>
</PSPLIBDOC>
